ksync/__init__.py
ksync/kmessage.py
ksync/ksync.py
ksync-0.4.1.dist-info/LICENSE
ksync-0.4.1.dist-info/WHEEL
ksync-0.4.1.dist-info/METADATA
ksync-0.4.1.dist-info/RECORD
